django_xblog-0.3.1.dist-info/licenses/LICENSE
xblog/__init__.py
xblog/admin.py
xblog/context_processors.py
xblog/feeds.py
xblog/forms.py
xblog/import_rss.py
xblog/mechanic.py
xblog/metaWeblog.py
xblog/models.py
xblog/ping_modes.py
xblog/pipeline.py
xblog/podcast_utils.py
xblog/requirements.txt
xblog/search_indexes.py
xblog/trackbacktest.py
xblog/urls.py
xblog/xmlrpc.py
xblog/xmlrpc_settings.py
xblog/external/BeautifulSoup.py
xblog/external/__init__.py
xblog/external/akismet.py
xblog/external/fuzzyclock.py
xblog/external/mdx_footnotes.py
xblog/external/mdx_rss.py
xblog/external/postutils.py
xblog/external/setup.py
xblog/external/smartypants.py
xblog/external/text_stats.py
xblog/management/__init__.py
xblog/management/commands/__init__.py
xblog/management/commands/populate.py
xblog/management/commands/xblog_import.py
xblog/migrations/0001_initial.py
xblog/migrations/0002_blog_default_comments_status_and_more.py
xblog/migrations/__init__.py
xblog/static/js/utils.js
xblog/static/pygments-css/README.rst
xblog/static/pygments-css/UNLICENSE.txt
xblog/static/pygments-css/autumn.css
xblog/static/pygments-css/borland.css
xblog/static/pygments-css/bw.css
xblog/static/pygments-css/colorful.css
xblog/static/pygments-css/default.css
xblog/static/pygments-css/emacs.css
xblog/static/pygments-css/friendly.css
xblog/static/pygments-css/fruity.css
xblog/static/pygments-css/github.css
xblog/static/pygments-css/manni.css
xblog/static/pygments-css/monokai.css
xblog/static/pygments-css/murphy.css
xblog/static/pygments-css/native.css
xblog/static/pygments-css/pastie.css
xblog/static/pygments-css/perldoc.css
xblog/static/pygments-css/tango.css
xblog/static/pygments-css/trac.css
xblog/static/pygments-css/vim.css
xblog/static/pygments-css/vs.css
xblog/static/pygments-css/zenburn.css
xblog/static/xblog-css/bootsrap-min.css
xblog/static/xblog-css/split-pane.css
xblog/static/xblog-css/xblog.css
xblog/templates/feeds/blogs_description.html
xblog/templates/feeds/blogs_title.html
xblog/templates/feeds/podcast_description.html
django_xblog-0.3.1.dist-info/METADATA
django_xblog-0.3.1.dist-info/WHEEL
django_xblog-0.3.1.dist-info/top_level.txt
django_xblog-0.3.1.dist-info/RECORD
