Metadata-Version: 2.4
Name: django-xblog
Version: 0.3.1
Summary: A full-featured blogging application for your Django site
Home-page: https://github.com/rubeon/django-xblog
Author: Eric Williams
Author-email: eric@ehw.io
License: BSD License
Keywords: django,blog,weblog,bootstrap,metaWeblog,wordpress
Classifier: Framework :: Django :: 1.8
Classifier: Development Status :: 3 - Alpha
Classifier: Environment :: Web Environment
Classifier: Programming Language :: Python
Classifier: Intended Audience :: Developers
Classifier: Operating System :: OS Independent
Classifier: License :: OSI Approved :: BSD License
License-File: LICENSE
Requires-Dist: django
Requires-Dist: html2text
Requires-Dist: BeautifulSoup4
Requires-Dist: django-markdown-deux
Requires-Dist: Pillow
Requires-Dist: pytz
Requires-Dist: textstat
Requires-Dist: pygments
Requires-Dist: django-xmlrpc-dx
Requires-Dist: six
Dynamic: author
Dynamic: author-email
Dynamic: classifier
Dynamic: description
Dynamic: description-content-type
Dynamic: home-page
Dynamic: keywords
Dynamic: license
Dynamic: license-file
Dynamic: requires-dist
Dynamic: summary
